<lcgdict>
  <class name="T_TPCnv<LumiBlockCollection,LumiBlockCollection_p2>"/>
  <class name="LumiBlockCollectionCnv_p2"/>
  <class name="T_AthenaPoolTPCnvBase<LumiBlockCollection,LumiBlockCollection_p2>"/>
  <class name="T_AthenaPoolTPPolyCnvBase<LumiBlockCollection,LumiBlockCollection,LumiBlockCollection_p2>"/>
  <class name="T_AthenaPoolTPAbstractPolyCnvBase<LumiBlockCollection,LumiBlockCollection,LumiBlockCollection_p2>"/>
  <class name="ITPConverterFor<LumiBlockCollection>"/>
  <class name="T_TPCnv<LB_IOVRange,LumiBlockRange_p2>"/>
  <class name="LumiBlockRangeCnv_p2"/>
  <class name="T_AthenaPoolTPCnvBase<LB_IOVRange,LumiBlockRange_p2>"/>
  <class name="ITPConverterFor<LB_IOVRange>"/>
</lcgdict>
