<?xml version="1.0"?>
<MethodSetup Method="MLP::MLP_N3.pt1000_eta2.37_conv2">
  <GeneralInfo>
    <Info name="TMVA Release" value="4.1.0 [262400]"/>
    <Info name="ROOT Release" value="5.28/00 [334848]"/>
    <Info name="Creator" value="jsaxon"/>
    <Info name="Date" value="Sat Jun 23 16:07:28 2012"/>
    <Info name="Host" value="Linux lxbuild148.cern.ch 2.6.18-194.26.1.el5 #1 SMP Wed Nov 10 09:45:46 CET 2010 x86_64 x86_64 x86_64 GNU/Linux"/>
    <Info name="Dir" value="/home/jsaxon/NeuralNetworks/nn12"/>
    <Info name="Training events" value="20000"/>
    <Info name="TrainingTime" value="307.132"/>
    <Info name="AnalysisType" value="Classification"/>
  </GeneralInfo>
  <Options>
    <Option name="NCycles" modified="Yes">2000</Option>
    <Option name="HiddenLayers" modified="Yes">N+3</Option>
    <Option name="NeuronType" modified="Yes">tanh</Option>
    <Option name="RandomSeed" modified="No">1</Option>
    <Option name="EstimatorType" modified="No">MSE</Option>
    <Option name="NeuronInputType" modified="No">sum</Option>
    <Option name="V" modified="No">False</Option>
    <Option name="VerbosityLevel" modified="No">Default</Option>
    <Option name="VarTransform" modified="Yes">N</Option>
    <Option name="H" modified="No">False</Option>
    <Option name="CreateMVAPdfs" modified="No">False</Option>
    <Option name="IgnoreNegWeightsInTraining" modified="No">False</Option>
    <Option name="TrainingMethod" modified="No">BP</Option>
    <Option name="LearningRate" modified="No">2.000000e-02</Option>
    <Option name="DecayRate" modified="No">1.000000e-02</Option>
    <Option name="TestRate" modified="Yes">5</Option>
    <Option name="EpochMonitoring" modified="No">False</Option>
    <Option name="Sampling" modified="No">1.000000e+00</Option>
    <Option name="SamplingEpoch" modified="No">1.000000e+00</Option>
    <Option name="SamplingImportance" modified="No">1.000000e+00</Option>
    <Option name="SamplingTraining" modified="No">True</Option>
    <Option name="SamplingTesting" modified="No">False</Option>
    <Option name="ResetStep" modified="No">50</Option>
    <Option name="Tau" modified="No">3.000000e+00</Option>
    <Option name="BPMode" modified="No">sequential</Option>
    <Option name="BatchSize" modified="No">-1</Option>
    <Option name="ConvergenceImprove" modified="No">1.000000e-30</Option>
    <Option name="ConvergenceTests" modified="Yes">20</Option>
    <Option name="UseRegulator" modified="Yes">False</Option>
    <Option name="UpdateLimit" modified="No">10</Option>
    <Option name="CalculateErrors" modified="No">False</Option>
  </Options>
  <Variables NVar="10">
    <Variable VarIndex="0" Expression="fside" Label="fside" Title="fside" Unit="" Internal="fside" Type="D" Min="0.114931" Max="1.53314"/>
    <Variable VarIndex="1" Expression="w1" Label="w1" Title="w1" Unit="" Internal="w1" Type="D" Min="0.380304" Max="0.812234"/>
    <Variable VarIndex="2" Expression="wtot" Label="wtot" Title="wtot" Unit="" Internal="wtot" Type="D" Min="0.959497" Max="4.53832"/>
    <Variable VarIndex="3" Expression="deltae" Label="deltae" Title="deltae" Unit="" Internal="deltae" Type="D" Min="-6019.54" Max="42706.5"/>
    <Variable VarIndex="4" Expression="eratio" Label="eratio" Title="eratio" Unit="" Internal="eratio" Type="D" Min="0.000249184" Max="1.00134"/>
    <Variable VarIndex="5" Expression="rphi" Label="rphi" Title="rphi" Unit="" Internal="rphi" Type="D" Min="0.532577" Max="0.972732"/>
    <Variable VarIndex="6" Expression="rhad" Label="rhad" Title="rhad" Unit="" Internal="rhad" Type="D" Min="-0.00963353" Max="0.0139971"/>
    <Variable VarIndex="7" Expression="reta" Label="reta" Title="reta" Unit="" Internal="reta" Type="D" Min="0.908013" Max="0.953937"/>
    <Variable VarIndex="8" Expression="weta2" Label="weta2" Title="weta2" Unit="" Internal="weta2" Type="D" Min="0.0102731" Max="0.0129995"/>
    <Variable VarIndex="9" Expression="f1" Label="f1" Title="f1" Unit="" Internal="f1" Type="D" Min="0.0321734" Max="0.483369"/>
  </Variables>
  <Spectators NSpec="4">
    <Spectator SpecIndex="0" Expression="pt" Label="pt" Title="P_{T} [GeV]" Unit="D" Internal="pt" Type="F" Min="80000.6" Max="528816"/>
    <Spectator SpecIndex="1" Expression="etas2" Label="etas2" Title="etas2" Unit="D" Internal="etas2" Type="F" Min="-2.36984" Max="2.3699"/>
    <Spectator SpecIndex="2" Expression="convFlag" Label="convFlag" Title="convFlag" Unit="i" Internal="convFlag" Type="F" Min="2" Max="12"/>
    <Spectator SpecIndex="3" Expression="tight" Label="tight" Title="Tight" Unit="i" Internal="tight" Type="F" Min="0" Max="1"/>
  </Spectators>
  <Transformations NTransformations="1">
    <Transform Name="Normalize" NVariables="10" NTargets="0">
      <Class ClassIndex="0">
        <Variables>
          <Variable VarIndex="0" Min="1.1493124812841415e-01" Max="3.7442404031753540e-01"/>
          <Variable VarIndex="1" Min="3.8030400872230530e-01" Max="7.4854934215545654e-01"/>
          <Variable VarIndex="2" Min="9.5949685573577881e-01" Max="2.8318598270416260e+00"/>
          <Variable VarIndex="3" Min="-1.8787280273437500e+02" Max="4.2706457031250000e+04"/>
          <Variable VarIndex="4" Min="1.5122185461223125e-02" Max="1.0013425350189209e+00"/>
          <Variable VarIndex="5" Min="8.4598696231842041e-01" Max="9.6862554550170898e-01"/>
          <Variable VarIndex="6" Min="-8.9248791337013245e-03" Max="1.3895503245294094e-02"/>
          <Variable VarIndex="7" Min="9.0830707550048828e-01" Max="9.5291924476623535e-01"/>
          <Variable VarIndex="8" Min="1.0286659002304077e-02" Max="1.2895187363028526e-02"/>
          <Variable VarIndex="9" Min="7.1971669793128967e-02" Max="4.8336881399154663e-01"/>
        </Variables>
        <Targets/>
      </Class>
      <Class ClassIndex="1">
        <Variables>
          <Variable VarIndex="0" Min="1.1752863973379135e-01" Max="1.5331395864486694e+00"/>
          <Variable VarIndex="1" Min="4.0744718909263611e-01" Max="8.1223416328430176e-01"/>
          <Variable VarIndex="2" Min="1.0432114601135254e+00" Max="4.5383181571960449e+00"/>
          <Variable VarIndex="3" Min="-6.0195449218750000e+03" Max="3.5875863281250000e+04"/>
          <Variable VarIndex="4" Min="2.4918388226069510e-04" Max="1.0000000000000000e+00"/>
          <Variable VarIndex="5" Min="5.3257715702056885e-01" Max="9.7273248434066772e-01"/>
          <Variable VarIndex="6" Min="-9.6335308626294136e-03" Max="1.3997071422636509e-02"/>
          <Variable VarIndex="7" Min="9.0801280736923218e-01" Max="9.5393711328506470e-01"/>
          <Variable VarIndex="8" Min="1.0273133404552937e-02" Max="1.2999461032450199e-02"/>
          <Variable VarIndex="9" Min="3.2173365354537964e-02" Max="4.8184782266616821e-01"/>
        </Variables>
        <Targets/>
      </Class>
      <Class ClassIndex="2">
        <Variables>
          <Variable VarIndex="0" Min="1.1493124812841415e-01" Max="1.5331395864486694e+00"/>
          <Variable VarIndex="1" Min="3.8030400872230530e-01" Max="8.1223416328430176e-01"/>
          <Variable VarIndex="2" Min="9.5949685573577881e-01" Max="4.5383181571960449e+00"/>
          <Variable VarIndex="3" Min="-6.0195449218750000e+03" Max="4.2706457031250000e+04"/>
          <Variable VarIndex="4" Min="2.4918388226069510e-04" Max="1.0013425350189209e+00"/>
          <Variable VarIndex="5" Min="5.3257715702056885e-01" Max="9.7273248434066772e-01"/>
          <Variable VarIndex="6" Min="-9.6335308626294136e-03" Max="1.3997071422636509e-02"/>
          <Variable VarIndex="7" Min="9.0801280736923218e-01" Max="9.5393711328506470e-01"/>
          <Variable VarIndex="8" Min="1.0273133404552937e-02" Max="1.2999461032450199e-02"/>
          <Variable VarIndex="9" Min="3.2173365354537964e-02" Max="4.8336881399154663e-01"/>
        </Variables>
        <Targets/>
      </Class>
    </Transform>
  </Transformations>
  <MVAPdfs/>
  <Weights>
    <Layout NLayers="3">
      <Layer Index="0" NNeurons="11">
        <Neuron NSynapses="13">
          -7.3125558430295123e-01 1.1476753253417609e+00 3.0867273328099787e-01 1.8886105223381515e+00 -2.2942382138608903e+00 -1.1672442813067287e+00 -2.7054402465007654e-01 1.7181431655045734e+00 -6.6730670144435067e-01 -1.2008480251138369e+00 -1.6654398299943074e+00 -1.1239042556660146e+00 -2.8645568687806748e+00 
        </Neuron>
        <Neuron NSynapses="13">
          -6.0288399859256347e-01 6.9649616645787948e-01 4.3070551656636930e-01 -4.2924334710094897e-01 1.3842636352559337e+00 -4.0806751226071303e-01 1.4127472818605447e+00 -7.5756766342631221e-01 2.3344656876043812e+00 9.4793712647272643e-01 -9.7123511545558938e-01 -7.6233949495768283e-01 -2.0488842692942608e+00 
        </Neuron>
        <Neuron NSynapses="13">
          3.9141425722621304e-01 1.1094599016825080e+00 -1.8604308228312043e+00 4.7888486098865318e-01 8.7756603038227465e-02 1.5404209163279885e+00 1.2970279818392186e-01 -1.1784552173562070e-01 6.4206462789235341e-01 -6.9044103644161403e-01 -1.5139230824683834e+00 1.2040896618531001e+00 -1.6021356445670294e+00 
        </Neuron>
        <Neuron NSynapses="13">
          2.4211844305969257e-01 3.3144962958818819e-01 8.0151327229031655e-01 1.8742194956724783e+00 5.5206724257496509e-01 -1.5333893483299235e+00 -1.1539493611674803e+00 9.6734826723584344e-01 -6.3324210239035095e-01 1.1579282332075043e+00 6.1565040635570178e-01 1.0004906933486688e+00 2.6512972701460744e+00 
        </Neuron>
        <Neuron NSynapses="13">
          -1.3142302998702735e+00 2.7930416909806555e+00 -2.2155037063105798e+00 -7.7909858145696148e-02 -9.7051107120767577e-01 -2.3909704163927534e+00 1.2476620670294887e+00 6.8052693712844314e-01 -1.0261832088165177e+00 2.2749792380149900e-01 -2.8787526427874242e+00 1.6227425706834002e+00 2.0137185596561498e+00 
        </Neuron>
        <Neuron NSynapses="13">
          -1.9058807224019814e-01 2.3426013167457754e-01 -4.9878679208796045e-01 -1.3653775137603130e-01 -8.1258598906401458e-01 -3.5895803187490696e+00 -2.0508390069088751e+00 6.8540114633130444e-01 8.2724149346759146e-01 6.2671448501377680e-01 6.8387570701775446e-01 -1.1333935428520050e+00 2.7901581228192787e+00 
        </Neuron>
        <Neuron NSynapses="13">
          1.3481801844133436e+00 2.6946593368822647e-01 2.3197887566972644e+00 3.9822858298683939e-01 1.0583657040009966e+00 3.4429226455572898e-01 -9.6370368607912149e-01 -6.6648850120161293e-02 1.1211885097080789e+00 -8.7145283980263066e-01 -6.2111603414862282e-01 -1.0463366490375978e+00 -1.7567549270360208e+00 
        </Neuron>
        <Neuron NSynapses="13">
          -9.5596248668381767e-01 2.7527874153118930e+00 -1.4849067306933541e+00 -4.3835838922876952e-01 3.4676556092857946e-01 -2.7000831014562001e+00 -1.4886889409395458e+00 -7.7780641901136816e-01 -1.1875469863990997e+00 -1.3302814469309781e+00 -2.7486424331077104e+00 4.1241210122636524e-01 1.1896088701527630e+00 
        </Neuron>
        <Neuron NSynapses="13">
          -1.6417113920887931e+00 3.1394342723618212e+00 -1.7515650911701699e+00 -7.7611636984234256e-01 3.0093285775479258e-02 -2.0565137312874180e+00 -1.9469236414756541e+00 -1.1479026534184676e-01 2.3905491331299769e+00 -1.2896729450157421e-01 -3.6929869742667103e+00 1.2980879669176437e+00 -7.4800990009998958e-01 
        </Neuron>
        <Neuron NSynapses="13">
          -4.2402714502850480e-01 -8.6624806230761708e-01 -5.2799932048868659e-01 -1.2965944158471019e+00 1.0939339022240617e-01 9.9099260139019041e-02 1.9075772634432364e+00 1.3275807607618118e-01 -1.4408190834051311e+00 -3.6663687418603841e-01 1.3213813246508384e+00 -2.2331567714297771e+00 1.7557086386094307e+00 
        </Neuron>
        <Neuron NSynapses="13">
          1.3222539016980144e+00 -1.9885022120878264e+00 1.2492091832303178e+00 -2.4046486489032124e+00 9.7517787165847536e-01 4.1066949465042963e+00 1.0351400995621023e+00 -2.2552593168244282e+00 8.3464995903794992e-01 2.2614119172046956e+00 1.9425725600646475e+00 1.0097428618248048e+00 -6.3664430670358918e+00 
        </Neuron>
      </Layer>
      <Layer Index="1" NNeurons="14">
        <Neuron NSynapses="1">
          1.8548706532570949e-01 
        </Neuron>
        <Neuron NSynapses="1">
          -9.7373926593352889e-01 
        </Neuron>
        <Neuron NSynapses="1">
          -1.9055852774704135e-01 
        </Neuron>
        <Neuron NSynapses="1">
          1.0064159119247549e+00 
        </Neuron>
        <Neuron NSynapses="1">
          7.5316190524552282e-02 
        </Neuron>
        <Neuron NSynapses="1">
          -2.2769644725543725e-01 
        </Neuron>
        <Neuron NSynapses="1">
          1.8574565701329059e-02 
        </Neuron>
        <Neuron NSynapses="1">
          -1.7862726301242129e-01 
        </Neuron>
        <Neuron NSynapses="1">
          1.9646127352788065e-01 
        </Neuron>
        <Neuron NSynapses="1">
          2.5046963256777255e-01 
        </Neuron>
        <Neuron NSynapses="1">
          -7.8849693233309748e-01 
        </Neuron>
        <Neuron NSynapses="1">
          -7.2815180921567038e-02 
        </Neuron>
        <Neuron NSynapses="1">
          4.5987890497035716e-01 
        </Neuron>
        <Neuron NSynapses="1">
          8.0680023176616811e-01 
        </Neuron>
      </Layer>
      <Layer Index="2" NNeurons="1">
        <Neuron NSynapses="0"/>
      </Layer>
    </Layout>
  </Weights>
</MethodSetup>
